{
  "fontSize": 11,
  "windowPositions": {
    "filtro_agronomia_unidad": "agrodata",
    "window_state_bitacora": {
      "position": {
        "x": 220,
        "y": 140
      },
      "size": {
        "width": 900,
        "height": 600
      },
      "isMinimized": false,
      "isMaximized": false,
      "prevState": {
        "position": {
          "x": 220,
          "y": 140
        },
        "size": {
          "width": 900,
          "height": 600
        }
      }
    },
    "filtro_reparaciones_unidad": "luvica",
    "window_state_agronomia": {
      "position": {
        "x": 412,
        "y": 110
      },
      "size": {
        "width": 1000,
        "height": 600
      },
      "isMinimized": false,
      "isMaximized": false,
      "prevState": {
        "position": {
          "x": 160,
          "y": 100
        },
        "size": {
          "width": 1000,
          "height": 600
        }
      }
    },
    "filtro_cheques_unidad": "all",
    "window_state_reparaciones": {
      "position": {
        "x": 416,
        "y": 124
      },
      "size": {
        "width": 1000,
        "height": 600
      },
      "isMinimized": false,
      "isMaximized": false,
      "prevState": {
        "position": {
          "x": 200,
          "y": 120
        },
        "size": {
          "width": 1000,
          "height": 600
        }
      }
    },
    "filtro_cosecha_unidad": "agrodata",
    "filtro_bancos_banco": "bancamiga",
    "window_state_debug-window": {
      "position": {
        "x": 538,
        "y": 360
      },
      "size": {
        "width": 500,
        "height": 500
      },
      "isMinimized": false,
      "prevState": {
        "position": {
          "x": 300,
          "y": 100
        },
        "size": {
          "width": 500,
          "height": 500
        }
      }
    },
    "filtro_transferencias_banco": "all",
    "window_state_menu-principal": {
      "position": {
        "x": 16,
        "y": 16
      },
      "size": {
        "width": 300,
        "height": 556
      },
      "isMinimized": false,
      "isMaximized": false,
      "prevState": {
        "position": {
          "x": 16,
          "y": 16
        },
        "size": {
          "width": 200,
          "height": 400
        }
      }
    },
    "window_state_manual-usuario": {
      "position": {
        "x": 100,
        "y": 50
      },
      "size": {
        "width": 500,
        "height": 600
      },
      "isMinimized": false,
      "prevState": {
        "position": {
          "x": 100,
          "y": 50
        },
        "size": {
          "width": 500,
          "height": 600
        }
      }
    },
    "window_state_reportes": {
      "position": {
        "x": 360,
        "y": 56
      },
      "size": {
        "width": 900,
        "height": 540
      },
      "isMinimized": false,
      "isMaximized": false,
      "prevState": {
        "position": {
          "x": 360,
          "y": 56
        },
        "size": {
          "width": 900,
          "height": 540
        }
      }
    },
    "filtro_almacen_unidad": "luvica",
    "filtro_administracion_unidad": "finca valeria",
    "window_state_mydebug-window": {
      "position": {
        "x": 300,
        "y": 100
      },
      "size": {
        "width": 550,
        "height": 600
      },
      "isMinimized": true,
      "isMaximized": false,
      "prevState": {
        "position": {
          "x": 300,
          "y": 100
        },
        "size": {
          "width": 550,
          "height": 600
        }
      }
    },
    "filtro_bitacora_unidad": "agrodata",
    "filtro_transferencias_unidad": "finca valeria"
  },
  "theme": "light",
  "colorScheme": "lightblue",
  "savedAt": "2026-02-20T23:33:18.776Z"
}